fds/__init__.py
fds/sdk/__init__.py
fds/sdk/CompanyLogo/__init__.py
fds/sdk/CompanyLogo/api_client.py
fds/sdk/CompanyLogo/configuration.py
fds/sdk/CompanyLogo/exceptions.py
fds/sdk/CompanyLogo/model_utils.py
fds/sdk/CompanyLogo/rest.py
fds/sdk/CompanyLogo/api/__init__.py
fds/sdk/CompanyLogo/api/company_api.py
fds/sdk/CompanyLogo/apis/__init__.py
fds/sdk/CompanyLogo/model/__init__.py
fds/sdk/CompanyLogo/model/inline_response200.py
fds/sdk/CompanyLogo/model/inline_response200_data.py
fds/sdk/CompanyLogo/model/inline_response200_data_large.py
fds/sdk/CompanyLogo/model/inline_response200_data_medium.py
fds/sdk/CompanyLogo/model/inline_response200_data_small.py
fds/sdk/CompanyLogo/model/inline_response200_data_vector.py
fds/sdk/CompanyLogo/model/inline_response200_meta.py
fds/sdk/CompanyLogo/model/status_object.py
fds/sdk/CompanyLogo/models/__init__.py
fds.sdk.CompanyLogo-0.20.1.dist-info/LICENSE
fds.sdk.CompanyLogo-0.20.1.dist-info/METADATA
fds.sdk.CompanyLogo-0.20.1.dist-info/WHEEL
fds.sdk.CompanyLogo-0.20.1.dist-info/top_level.txt
fds.sdk.CompanyLogo-0.20.1.dist-info/RECORD
